avologger/__init__.py
avologger/avologger.py
avologger-1.0.4.dist-info/LICENSE
avologger-1.0.4.dist-info/METADATA
avologger-1.0.4.dist-info/WHEEL
avologger-1.0.4.dist-info/top_level.txt
avologger-1.0.4.dist-info/RECORD
