Metadata-Version: 2.1
Name: avologger
Version: 1.0.4
Summary: A generic logging class
Home-page: 
Author: Chris O'Brien
Author-email: cobrien@avophotonics.com
Classifier: Programming Language :: Python :: 3
Classifier: License :: OSI Approved :: MIT License
Classifier: Operating System :: OS Independent
Requires-Python: >=3.0
License-File: LICENSE
